nyaatimer/__init__.py
nyaa_timer-2.0.0.dist-info/METADATA
nyaa_timer-2.0.0.dist-info/WHEEL
nyaa_timer-2.0.0.dist-info/top_level.txt
nyaa_timer-2.0.0.dist-info/RECORD
