Metadata-Version: 2.1
Name: nyaa-timer
Version: 2.0.0
Summary: A simple nyaa_timer decorator to calculate the elapsed time of a function
Author: Praveen Senpai
Author-email: pvnt20@gmail.com
Requires-Dist: rich
